{
  "version": "5.5",
  "verified": false,
  "track": 3,
  "name": "Hler's Serenity Focused Supply A",
  "type": "focused-supply-a",
  "token": "focused-supply-card",
  "featured": [
    {
      "type": "weapon",
      "id": "hler-s-serenity"
    },
    {
      "type": "stigmata",
      "id": "dante-top"
    },
    {
      "type": "stigmata",
      "id": "dante-mid"
    },
    {
      "type": "stigmata",
      "id": "dante-bot"
    }
  ],
  "extra": [],
  "duration": ["2022-03-18", "2022-03-25"],
  "guarantees": [
    {
      "count": 10,
      "recurring": true,
      "rewards": [
        {
          "type": "stigmata",
          "id": "4star-stigmata-in-drops",
          "amount": 1
        },
        {
          "type": "weapon",
          "id": "4star-weapon-in-drops",
          "amount": 1
        }
      ]
    }
  ],
  "mileages": [],
  "drops": [
    {
      "rate": 2479,
      "items": [
        {
          "type": "weapon",
          "id": "hler-s-serenity",
          "amount": 1
        }
      ]
    },
    {
      "rate": 1240,
      "items": [
        {
          "type": "stigmata",
          "id": "dante-top",
          "amount": 1
        }
      ]
    },
    {
      "rate": 1240,
      "items": [
        {
          "type": "stigmata",
          "id": "dante-mid",
          "amount": 1
        }
      ]
    },
    {
      "rate": 1240,
      "items": [
        {
          "type": "stigmata",
          "id": "dante-bot",
          "amount": 1
        }
      ]
    },
    {
      "rate": 413,
      "items": [
        {
          "type": "weapon",
          "id": "keys-of-the-void",
          "amount": 1
        }
      ]
    },
    {
      "rate": 413,
      "items": [
        {
          "type": "weapon",
          "id": "dawn-breaker-talwar",
          "amount": 1
        }
      ]
    },
    {
      "rate": 413,
      "items": [
        {
          "type": "weapon",
          "id": "vikrantstar-shatterer-vikrant",
          "amount": 1
        }
      ]
    },
    {
      "rate": 413,
      "items": [
        {
          "type": "weapon",
          "id": "godslayer-surtr",
          "amount": 1
        }
      ]
    },
    {
      "rate": 460,
      "items": [
        {
          "type": "weapon",
          "id": "nuada-s-grief",
          "amount": 1
        }
      ]
    },
    {
      "rate": 413,
      "items": [
        {
          "type": "weapon",
          "id": "path-to-acheron",
          "amount": 1
        }
      ]
    },
    {
      "rate": 310,
      "items": [
        {
          "type": "stigmata",
          "id": "allan-poe-top",
          "amount": 1
        }
      ]
    },
    {
      "rate": 310,
      "items": [
        {
          "type": "stigmata",
          "id": "allan-poe-mid",
          "amount": 1
        }
      ]
    },
    {
      "rate": 310,
      "items": [
        {
          "type": "stigmata",
          "id": "allan-poe-bot",
          "amount": 1
        }
      ]
    },
    {
      "rate": 310,
      "items": [
        {
          "type": "stigmata",
          "id": "holmes-top",
          "amount": 1
        }
      ]
    },
    {
      "rate": 310,
      "items": [
        {
          "type": "stigmata",
          "id": "holmes-mid",
          "amount": 1
        }
      ]
    },
    {
      "rate": 310,
      "items": [
        {
          "type": "stigmata",
          "id": "holmes-bot",
          "amount": 1
        }
      ]
    },
    {
      "rate": 310,
      "items": [
        {
          "type": "stigmata",
          "id": "kafka-top",
          "amount": 1
        }
      ]
    },
    {
      "rate": 310,
      "items": [
        {
          "type": "stigmata",
          "id": "kafka-mid",
          "amount": 1
        }
      ]
    },
    {
      "rate": 310,
      "items": [
        {
          "type": "stigmata",
          "id": "kafka-bot",
          "amount": 1
        }
      ]
    },
    {
      "rate": 310,
      "items": [
        {
          "type": "stigmata",
          "id": "dirac-top",
          "amount": 1
        }
      ]
    },
    {
      "rate": 310,
      "items": [
        {
          "type": "stigmata",
          "id": "dirac-mid",
          "amount": 1
        }
      ]
    },
    {
      "rate": 310,
      "items": [
        {
          "type": "stigmata",
          "id": "dirac-bot",
          "amount": 1
        }
      ]
    }
  ]
}
