{
  "id": "betrayer",
  "name": "Betrayer",
  "category": "greatsword",
  "atk": 245,
  "crt": 15,
  "rarity": 5,
  "skills": [
    {
      "name": "Treason",
      "description": "[SP: 18][CD: 12s] Launches 6 homing missiles in a row, each dealing 200% ATK of Physical DMG to the target an nearby enemies in a small AOE. Hit enemies are stunned for 2.53s."
    },
    {
      "name": "Betrayer's Counter",
      "description": "When attacked, gain a 49% chance of dealing 157% ATK of Physical DMG."
    }
  ]
}
