{
  "version": "5.7",
  "verified": true,
  "track": 3,
  "name": "Astral Rend: White Dwarf Focused Supply A",
  "featured": [
    {
      "type": "weapon",
      "id": "astral-rend-white-dwarf"
    },
    {
      "type": "stigmata",
      "id": "ragna-top"
    },
    {
      "type": "stigmata",
      "id": "ragna-mid"
    },
    {
      "type": "stigmata",
      "id": "ragna-bot"
    }
  ],
  "duration": ["2022-06-17", "2022-06-24"],
  "others": [
    {
      "type": "weapon",
      "id": "tranquil-arias"
    },
    {
      "type": "weapon",
      "id": "key-of-castigation"
    },
    {
      "type": "weapon",
      "id": "swan-lake"
    },
    {
      "type": "weapon",
      "id": "nebulous-duality"
    },
    {
      "type": "weapon",
      "id": "eos-gloria"
    },
    {
      "type": "weapon",
      "id": "iris-of-the-dreams"
    },
    {
      "type": "stigmata",
      "id": "irene-adler-top"
    },
    {
      "type": "stigmata",
      "id": "irene-adler-mid"
    },
    {
      "type": "stigmata",
      "id": "irene-adler-bot"
    },
    {
      "type": "stigmata",
      "id": "kafka-top"
    },
    {
      "type": "stigmata",
      "id": "kafka-mid"
    },
    {
      "type": "stigmata",
      "id": "kafka-bot"
    },
    {
      "type": "stigmata",
      "id": "verne-top"
    },
    {
      "type": "stigmata",
      "id": "verne-mid"
    },
    {
      "type": "stigmata",
      "id": "verne-bot"
    },
    {
      "type": "stigmata",
      "id": "elysia-top"
    },
    {
      "type": "stigmata",
      "id": "elysia-mid"
    },
    {
      "type": "stigmata",
      "id": "elysia-bot"
    }
  ]
}
